Calculator/Calculator.py
Calculator/__init__.py
calculator_linpel_calc-0.1.4.dist-info/LICENSE.txt
calculator_linpel_calc-0.1.4.dist-info/METADATA
calculator_linpel_calc-0.1.4.dist-info/WHEEL
calculator_linpel_calc-0.1.4.dist-info/top_level.txt
calculator_linpel_calc-0.1.4.dist-info/RECORD
