Metadata-Version: 2.1
Name: calculator-linpel-calc
Version: 0.1.4
Summary: Basic Python Calculator
Author: Linas Peleckas
Author-email: <peleckas.l@gmail.com>
Keywords: python,calculations
Classifier: Development Status :: 1 - Planning
Classifier: Intended Audience :: Developers
Classifier: Programming Language :: Python :: 3
Classifier: Operating System :: Unix
Classifier: Operating System :: MacOS :: MacOS X
Classifier: Operating System :: Microsoft :: Windows
License-File: LICENSE.txt
